sitesweeper/__init__.py
sitesweeper/__main__.py
sitesweeper/crawler.py
sitesweeper-1.0.2.dist-info/METADATA
sitesweeper-1.0.2.dist-info/WHEEL
sitesweeper-1.0.2.dist-info/top_level.txt
sitesweeper-1.0.2.dist-info/RECORD
