Metadata-Version: 2.1
Name: sitesweeper
Version: 1.0.2
Summary: Sitesweeper is a python package to help you automate your web scraping process, outputing pages to a file
Home-page: https://github.com/radityaharya/sitesweeper
Author: Raditya Harya
Author-email: contact@radityaharya.com
Requires-Dist: beautifulsoup4
Requires-Dist: pdfkit
Requires-Dist: requests
Requires-Dist: PyPDF2
Requires-Dist: lxml
